ft_package_abait_ta/__init__.py
ft_package_abait_ta/count_in_list.py
ft_package_abait_ta/count_occurence.py
ft_package_abait_ta-2024.0.0.2.dist-info/METADATA
ft_package_abait_ta-2024.0.0.2.dist-info/WHEEL
ft_package_abait_ta-2024.0.0.2.dist-info/licenses/LICENSE
ft_package_abait_ta-2024.0.0.2.dist-info/RECORD
