Metadata-Version: 2.3
Name: ft_package_abait_ta
Version: 2024.0.0.2
Summary: count occurence of a search_for elemnts with type any  in an iterbale list
Project-URL: Repository, https://github.com/Raxel01/42-python-piscine/tree/master/Day00/ex09
Author-email: ABDELALI AIT TALB <aittalbabdelalie@gmail.com>
License: The MIT License (MIT)
Keywords: easy_usage_package,helper_functions,simple_methodes
Classifier: Intended Audience :: Developers
Classifier: Programming Language :: Python :: 3.10
Requires-Python: >=3.10.15
